Metadata-Version: 2.1
Name: etext
Version: 0.0.1
Summary: Send sms and mms text messages for free using email
Home-page: https://github.com/AlfredoSequeida/etext
Author: Alfredo Sequeida
License: MIT
Download-URL: https://github.com/AlfredoSequeida/etext/archive/0.0.1.tar.gz
Keywords: sms,mms,text,text message,phone notification,email,short message service,multimedia messaging service
Platform: any
Classifier: Intended Audience :: End Users/Desktop
Classifier: License :: OSI Approved :: MIT License
Classifier: Programming Language :: Python :: 3
Classifier: Programming Language :: Python :: 3.6
Classifier: Programming Language :: Python :: 3.7
Classifier: Programming Language :: Python :: 3.8
Classifier: Programming Language :: Python :: 3.9
Classifier: Operating System :: Microsoft :: Windows :: Windows 10
Classifier: Operating System :: Microsoft :: Windows :: Windows 8
Classifier: Operating System :: Microsoft :: Windows :: Windows 8.1
Classifier: Operating System :: MacOS :: MacOS X
Classifier: Operating System :: POSIX :: Linux
Requires-Python: >=3.6
